src/pipeline_registers.v
// -----------------------------------------------------------------------------
// Module Group: Pipeline Registers
// Purpose:
//   These registers separate the 5 pipeline stages and pass data/control
//   signals forward each clock cycle.
//
// Included modules:
//   if_id_reg  : IF  -> ID
//   id_ex_reg  : ID  -> EX
//   ex_mem_reg : EX  -> MEM
//   mem_wb_reg : MEM -> WB
//
// Datapath connection:
//   Each module stores stage outputs at clock edge so the next stage can
//   process them in parallel during the following cycle.
// -----------------------------------------------------------------------------
// IF/ID Pipeline Register
// Transfers PC and instruction from IF stage to ID stage.
module if_id_reg (
    input  wire        clk,
    input  wire        reset,
    input  wire [31:0] if_pc,
    input  wire [31:0] if_instr,
    output reg  [31:0] id_pc,
    output reg  [31:0] id_instr
);
    always @(posedge clk or posedge reset) begin
        if (reset) begin
            id_pc    <= 32'b0;
            id_instr <= 32'h00000013;
        end else begin
            id_pc    <= if_pc;
            id_instr <= if_instr;
        end
    end
endmodule

module id_ex_reg (
    // ID/EX Pipeline Register
    // Transfers decoded operands, immediate, destination register,
    // and control signals from ID stage to EX stage.
    input  wire        clk,
    input  wire        reset,
    input  wire [31:0] id_pc,
    input  wire [31:0] id_read_data1,
    input  wire [31:0] id_read_data2,
    input  wire [31:0] id_imm,
    input  wire [4:0]  id_rs1,
    input  wire [4:0]  id_rs2,
    input  wire [4:0]  id_rd,
    input  wire [1:0]  id_alu_ctrl,
    input  wire        id_alu_src,
    input  wire        id_mem_read,
    input  wire        id_mem_write,
    input  wire        id_mem_to_reg,
    input  wire        id_reg_write,
    output reg  [31:0] ex_pc,
    output reg  [31:0] ex_read_data1,
    output reg  [31:0] ex_read_data2,
    output reg  [31:0] ex_imm,
    output reg  [4:0]  ex_rs1,
    output reg  [4:0]  ex_rs2,
    output reg  [4:0]  ex_rd,
    output reg  [1:0]  ex_alu_ctrl,
    output reg         ex_alu_src,
    output reg         ex_mem_read,
    output reg         ex_mem_write,
    output reg         ex_mem_to_reg,
    output reg         ex_reg_write
);
    always @(posedge clk or posedge reset) begin
        if (reset) begin
            ex_pc         <= 32'b0;
            ex_read_data1 <= 32'b0;
            ex_read_data2 <= 32'b0;
            ex_imm        <= 32'b0;
            ex_rs1        <= 5'b0;
            ex_rs2        <= 5'b0;
            ex_rd         <= 5'b0;
            ex_alu_ctrl   <= 2'b0;
            ex_alu_src    <= 1'b0;
            ex_mem_read   <= 1'b0;
            ex_mem_write  <= 1'b0;
            ex_mem_to_reg <= 1'b0;
            ex_reg_write  <= 1'b0;
        end else begin
            ex_pc         <= id_pc;
            ex_read_data1 <= id_read_data1;
            ex_read_data2 <= id_read_data2;
            ex_imm        <= id_imm;
            ex_rs1        <= id_rs1;
            ex_rs2        <= id_rs2;
            ex_rd         <= id_rd;
            ex_alu_ctrl   <= id_alu_ctrl;
            ex_alu_src    <= id_alu_src;
            ex_mem_read   <= id_mem_read;
            ex_mem_write  <= id_mem_write;
            ex_mem_to_reg <= id_mem_to_reg;
            ex_reg_write  <= id_reg_write;
        end
    end
endmodule

module ex_mem_reg (
    // EX/MEM Pipeline Register
    // Transfers ALU result, store data, destination register,
    // and memory/write-back control signals from EX to MEM.
    input  wire        clk,
    input  wire        reset,
    input  wire [31:0] ex_alu_result,
    input  wire [31:0] ex_write_data,
    input  wire [4:0]  ex_rd,
    input  wire        ex_mem_read,
    input  wire        ex_mem_write,
    input  wire        ex_mem_to_reg,
    input  wire        ex_reg_write,
    output reg  [31:0] mem_alu_result,
    output reg  [31:0] mem_write_data,
    output reg  [4:0]  mem_rd,
    output reg         mem_mem_read,
    output reg         mem_mem_write,
    output reg         mem_mem_to_reg,
    output reg         mem_reg_write
);
    always @(posedge clk or posedge reset) begin
        if (reset) begin
            mem_alu_result <= 32'b0;
            mem_write_data <= 32'b0;
            mem_rd         <= 5'b0;
            mem_mem_read   <= 1'b0;
            mem_mem_write  <= 1'b0;
            mem_mem_to_reg <= 1'b0;
            mem_reg_write  <= 1'b0;
        end else begin
            mem_alu_result <= ex_alu_result;
            mem_write_data <= ex_write_data;
            mem_rd         <= ex_rd;
            mem_mem_read   <= ex_mem_read;
            mem_mem_write  <= ex_mem_write;
            mem_mem_to_reg <= ex_mem_to_reg;
            mem_reg_write  <= ex_reg_write;
        end
    end
endmodule

module mem_wb_reg (
    // MEM/WB Pipeline Register
    // Transfers memory/ALU results and write-back control signals
    // from MEM stage to WB stage.
    input  wire        clk,
    input  wire        reset,
    input  wire [31:0] mem_read_data,
    input  wire [31:0] mem_alu_result,
    input  wire [4:0]  mem_rd,
    input  wire        mem_mem_to_reg,
    input  wire        mem_reg_write,
    output reg  [31:0] wb_read_data,
    output reg  [31:0] wb_alu_result,
    output reg  [4:0]  wb_rd,
    output reg         wb_mem_to_reg,
    output reg         wb_reg_write
);
    always @(posedge clk or posedge reset) begin
        if (reset) begin
            wb_read_data  <= 32'b0;
            wb_alu_result <= 32'b0;
            wb_rd         <= 5'b0;
            wb_mem_to_reg <= 1'b0;
            wb_reg_write  <= 1'b0;
        end else begin
            wb_read_data  <= mem_read_data;
            wb_alu_result <= mem_alu_result;
            wb_rd         <= mem_rd;
            wb_mem_to_reg <= mem_mem_to_reg;
            wb_reg_write  <= mem_reg_write;
        end
    end
endmodule

src/data_memory.v
// -----------------------------------------------------------------------------
// Module: Data Memory
// Purpose:
//   Provides data storage for load/store instructions.
//
// Inputs:
//   clk        : Clock used for synchronous store operations
//   mem_read   : Enables read for load instructions
//   mem_write  : Enables write for store instructions
//   addr       : Byte address from ALU result
//   write_data : Data to store (usually rs2 value)
//
// Output:
//   read_data : Data read from memory for load instructions
//
// Datapath connection:
//   EX stage computes address -> MEM stage accesses data memory.
//   Load result goes to MEM/WB for Write Back.
// -----------------------------------------------------------------------------
module data_memory (
    input  wire        clk,
    input  wire        mem_read,
    input  wire        mem_write,
    input  wire [31:0] addr,
    input  wire [31:0] write_data,
    output wire [31:0] read_data
);
    reg [31:0] mem [0:255];
    integer i;

    initial begin
        for (i = 0; i < 256; i = i + 1) begin
            mem[i] = 32'b0;
        end
    end

    // Synchronous store
    always @(posedge clk) begin
        if (mem_write) begin
            mem[addr[31:2]] <= write_data;
        end
    end

    // Combinational load
    assign read_data = mem_read ? mem[addr[31:2]] : 32'b0;
endmodule

src/alu.v
// Arithmetic Logic Unit (ALU)
// Supports ADD, SUB, AND, OR operations used in the EX stage.
// Inputs come from the register file/immediate path and output feeds MEM/WB path.
module alu (
    input  wire [31:0] a,
    input  wire [31:0] b,
    input  wire [1:0]  alu_ctrl,
    output reg  [31:0] result,
    output wire        zero
);
    localparam ALU_ADD = 2'b00;
    localparam ALU_SUB = 2'b01;
    localparam ALU_AND = 2'b10;
    localparam ALU_OR  = 2'b11;

    always @(*) begin
        case (alu_ctrl)
            ALU_ADD: result = a + b;
            ALU_SUB: result = a - b;
            ALU_AND: result = a & b;
            ALU_OR : result = a | b;
            default: result = 32'b0;
        endcase
    end

    assign zero = (result == 32'b0);
endmodule

src/register_file.v
// Register File
// 32 general-purpose 32-bit registers with 2 read ports and 1 write port.
// Register x0 is hardwired to zero.
// Read ports are used in ID stage and write-back data returns in WB stage.
module register_file (
    input  wire        clk,
    input  wire        reset,
    input  wire        reg_write,
    input  wire [4:0]  rs1,
    input  wire [4:0]  rs2,
    input  wire [4:0]  rd,
    input  wire [31:0] write_data,
    output wire [31:0] read_data1,
    output wire [31:0] read_data2
);
    integer i;
    reg [31:0] regs [0:31];

    always @(posedge clk or posedge reset) begin
        if (reset) begin
            for (i = 0; i < 32; i = i + 1) begin
                regs[i] <= 32'b0;
            end
        end else if (reg_write && (rd != 5'b0)) begin
            regs[rd] <= write_data;
        end
    end

    assign read_data1 = (rs1 == 5'b0) ? 32'b0 : regs[rs1];
    assign read_data2 = (rs2 == 5'b0) ? 32'b0 : regs[rs2];
endmodule

src/instruction_memory.v
// -----------------------------------------------------------------------------
// Module: Instruction Memory
// Purpose:
//   Stores the sample RISC-V program and returns one instruction per fetch.
//
// Input:
//   addr : 32-bit byte address from the Program Counter
//
// Output:
//   instruction : 32-bit instruction at the selected word address
//
// Datapath connection:
//   IF stage reads instruction using PC address.
//   Uses word alignment via addr[31:2] because instructions are 32-bit.
// -----------------------------------------------------------------------------
module instruction_memory (
    input  wire [31:0] addr,
    output wire [31:0] instruction
);
    reg [31:0] mem [0:255];

    // Word-aligned instruction fetch
    assign instruction = mem[addr[31:2]];

    initial begin
        integer i;
        for (i = 0; i < 256; i = i + 1) begin
            mem[i] = 32'h00000013; // NOP (addi x0, x0, 0)
        end

        // Sample program with NOP spacing for a pipeline without forwarding/stall logic:
        // x1 = 5
        // x2 = 10
        // x3 = x1 + x2 = 15
        // x4 = x2 - x1 = 5
        // MEM[0] = x3
        // x5 = MEM[0]
        // x6 = x1 & x2 = 0
        // x7 = x1 | x2 = 15
        // x8 = x5 + x4 = 20
        mem[0]  = 32'h00500093; // addi x1, x0, 5
        mem[1]  = 32'h00A00113; // addi x2, x0, 10
        mem[2]  = 32'h00000013; // nop
        mem[3]  = 32'h00000013; // nop
        mem[4]  = 32'h00000013; // nop
        mem[5]  = 32'h002081B3; // add x3, x1, x2
        mem[6]  = 32'h40110233; // sub x4, x2, x1
        mem[7]  = 32'h00000013; // nop
        mem[8]  = 32'h00000013; // nop
        mem[9]  = 32'h00000013; // nop
        mem[10] = 32'h00302023; // sw x3, 0(x0)
        mem[11] = 32'h00000013; // nop
        mem[12] = 32'h00000013; // nop
        mem[13] = 32'h00000013; // nop
        mem[14] = 32'h00002283; // lw x5, 0(x0)
        mem[15] = 32'h0020F333; // and x6, x1, x2
        mem[16] = 32'h0020E3B3; // or x7, x1, x2
        mem[17] = 32'h00000013; // nop
        mem[18] = 32'h00000013; // nop
        mem[19] = 32'h00000013; // nop
        mem[20] = 32'h00428433; // add x8, x5, x4
    end
endmodule

src/pc.v
// Program Counter (PC)
// Holds the current instruction address and updates every clock cycle.
// Drives instruction fetch by providing the address to instruction memory.
module pc (
	input  wire        clk,
	input  wire        reset,
	input  wire [31:0] next_pc,
	output reg  [31:0] pc_out
);
	always @(posedge clk or posedge reset) begin
		if (reset) begin
			pc_out <= 32'b0;
		end else begin
			pc_out <= next_pc;
		end
	end
endmodule

src/cpu_top.v
// Top-level 5-stage pipelined RISC-V CPU
// Connects IF, ID, EX, MEM, WB stages and their pipeline registers.
module cpu_top (
    input wire clk,
    input wire reset
);
    // ALU control encodings
    localparam ALU_ADD = 2'b00;
    localparam ALU_SUB = 2'b01;
    localparam ALU_AND = 2'b10;
    localparam ALU_OR  = 2'b11;

    // ---------------- IF stage ----------------
    wire [31:0] pc_current;
    wire [31:0] pc_next;
    wire [31:0] if_instruction;

    assign pc_next = pc_current + 32'd4;

    pc u_pc (
        .clk(clk),
        .reset(reset),
        .next_pc(pc_next),
        .pc_out(pc_current)
    );

    instruction_memory u_imem (
        .addr(pc_current),
        .instruction(if_instruction)
    );

    // IF/ID pipeline register
    wire [31:0] id_pc;
    wire [31:0] id_instruction;

    if_id_reg u_if_id (
        .clk(clk),
        .reset(reset),
        .if_pc(pc_current),
        .if_instr(if_instruction),
        .id_pc(id_pc),
        .id_instr(id_instruction)
    );

    // ---------------- ID stage ----------------
    wire [6:0] id_opcode;
    wire [2:0] id_funct3;
    wire [6:0] id_funct7;
    wire [4:0] id_rs1;
    wire [4:0] id_rs2;
    wire [4:0] id_rd;

    wire [31:0] id_imm_i;
    wire [31:0] id_imm_s;
    reg  [31:0] id_imm;

    reg  [1:0] id_alu_ctrl;
    reg        id_alu_src;
    reg        id_mem_read;
    reg        id_mem_write;
    reg        id_mem_to_reg;
    reg        id_reg_write;

    wire [31:0] id_read_data1;
    wire [31:0] id_read_data2;

    // WB stage signals used for register file write-back
    wire [4:0]  wb_rd;
    wire        wb_reg_write;
    wire [31:0] wb_write_data;

    assign id_opcode = id_instruction[6:0];
    assign id_rd     = id_instruction[11:7];
    assign id_funct3 = id_instruction[14:12];
    assign id_rs1    = id_instruction[19:15];
    assign id_rs2    = id_instruction[24:20];
    assign id_funct7 = id_instruction[31:25];

    assign id_imm_i = {{20{id_instruction[31]}}, id_instruction[31:20]};
    assign id_imm_s = {{20{id_instruction[31]}}, id_instruction[31:25], id_instruction[11:7]};

    register_file u_regfile (
        .clk(clk),
        .reset(reset),
        .reg_write(wb_reg_write),
        .rs1(id_rs1),
        .rs2(id_rs2),
        .rd(wb_rd),
        .write_data(wb_write_data),
        .read_data1(id_read_data1),
        .read_data2(id_read_data2)
    );

    // Main control + ALU control decode
    always @(*) begin
        // Defaults = NOP
        id_alu_ctrl   = ALU_ADD;
        id_alu_src    = 1'b0;
        id_mem_read   = 1'b0;
        id_mem_write  = 1'b0;
        id_mem_to_reg = 1'b0;
        id_reg_write  = 1'b0;
        id_imm        = 32'b0;

        case (id_opcode)
            7'b0110011: begin // R-type: add/sub/and/or
                id_alu_src    = 1'b0;
                id_reg_write  = 1'b1;
                case ({id_funct7, id_funct3})
                    10'b0000000_000: id_alu_ctrl = ALU_ADD;
                    10'b0100000_000: id_alu_ctrl = ALU_SUB;
                    10'b0000000_111: id_alu_ctrl = ALU_AND;
                    10'b0000000_110: id_alu_ctrl = ALU_OR;
                    default:         id_alu_ctrl = ALU_ADD;
                endcase
            end

            7'b0010011: begin // I-type ALU (only ADDI used here)
                id_alu_ctrl   = ALU_ADD;
                id_alu_src    = 1'b1;
                id_reg_write  = 1'b1;
                id_imm        = id_imm_i;
            end

            7'b0000011: begin // LW
                id_alu_ctrl   = ALU_ADD;
                id_alu_src    = 1'b1;
                id_mem_read   = 1'b1;
                id_mem_to_reg = 1'b1;
                id_reg_write  = 1'b1;
                id_imm        = id_imm_i;
            end

            7'b0100011: begin // SW
                id_alu_ctrl   = ALU_ADD;
                id_alu_src    = 1'b1;
                id_mem_write  = 1'b1;
                id_imm        = id_imm_s;
            end

            default: begin
                // Keep NOP defaults
            end
        endcase
    end

    // ID/EX pipeline register
    wire [31:0] ex_pc;
    wire [31:0] ex_read_data1;
    wire [31:0] ex_read_data2;
    wire [31:0] ex_imm;
    wire [4:0]  ex_rs1;
    wire [4:0]  ex_rs2;
    wire [4:0]  ex_rd;
    wire [1:0]  ex_alu_ctrl;
    wire        ex_alu_src;
    wire        ex_mem_read;
    wire        ex_mem_write;
    wire        ex_mem_to_reg;
    wire        ex_reg_write;

    id_ex_reg u_id_ex (
        .clk(clk),
        .reset(reset),
        .id_pc(id_pc),
        .id_read_data1(id_read_data1),
        .id_read_data2(id_read_data2),
        .id_imm(id_imm),
        .id_rs1(id_rs1),
        .id_rs2(id_rs2),
        .id_rd(id_rd),
        .id_alu_ctrl(id_alu_ctrl),
        .id_alu_src(id_alu_src),
        .id_mem_read(id_mem_read),
        .id_mem_write(id_mem_write),
        .id_mem_to_reg(id_mem_to_reg),
        .id_reg_write(id_reg_write),
        .ex_pc(ex_pc),
        .ex_read_data1(ex_read_data1),
        .ex_read_data2(ex_read_data2),
        .ex_imm(ex_imm),
        .ex_rs1(ex_rs1),
        .ex_rs2(ex_rs2),
        .ex_rd(ex_rd),
        .ex_alu_ctrl(ex_alu_ctrl),
        .ex_alu_src(ex_alu_src),
        .ex_mem_read(ex_mem_read),
        .ex_mem_write(ex_mem_write),
        .ex_mem_to_reg(ex_mem_to_reg),
        .ex_reg_write(ex_reg_write)
    );

    // ---------------- EX stage ----------------
    wire [31:0] ex_operand_b;
    wire [31:0] ex_alu_result;
    wire        ex_zero;

    assign ex_operand_b = ex_alu_src ? ex_imm : ex_read_data2;

    alu u_alu (
        .a(ex_read_data1),
        .b(ex_operand_b),
        .alu_ctrl(ex_alu_ctrl),
        .result(ex_alu_result),
        .zero(ex_zero)
    );

    // EX/MEM pipeline register
    wire [31:0] mem_alu_result;
    wire [31:0] mem_write_data;
    wire [4:0]  mem_rd;
    wire        mem_mem_read;
    wire        mem_mem_write;
    wire        mem_mem_to_reg;
    wire        mem_reg_write;

    ex_mem_reg u_ex_mem (
        .clk(clk),
        .reset(reset),
        .ex_alu_result(ex_alu_result),
        .ex_write_data(ex_read_data2),
        .ex_rd(ex_rd),
        .ex_mem_read(ex_mem_read),
        .ex_mem_write(ex_mem_write),
        .ex_mem_to_reg(ex_mem_to_reg),
        .ex_reg_write(ex_reg_write),
        .mem_alu_result(mem_alu_result),
        .mem_write_data(mem_write_data),
        .mem_rd(mem_rd),
        .mem_mem_read(mem_mem_read),
        .mem_mem_write(mem_mem_write),
        .mem_mem_to_reg(mem_mem_to_reg),
        .mem_reg_write(mem_reg_write)
    );

    // ---------------- MEM stage ----------------
    wire [31:0] mem_read_data;

    data_memory u_dmem (
        .clk(clk),
        .mem_read(mem_mem_read),
        .mem_write(mem_mem_write),
        .addr(mem_alu_result),
        .write_data(mem_write_data),
        .read_data(mem_read_data)
    );

    // MEM/WB pipeline register
    wire [31:0] wb_read_data;
    wire [31:0] wb_alu_result;
    wire        wb_mem_to_reg;

    mem_wb_reg u_mem_wb (
        .clk(clk),
        .reset(reset),
        .mem_read_data(mem_read_data),
        .mem_alu_result(mem_alu_result),
        .mem_rd(mem_rd),
        .mem_mem_to_reg(mem_mem_to_reg),
        .mem_reg_write(mem_reg_write),
        .wb_read_data(wb_read_data),
        .wb_alu_result(wb_alu_result),
        .wb_rd(wb_rd),
        .wb_mem_to_reg(wb_mem_to_reg),
        .wb_reg_write(wb_reg_write)
    );

    // ---------------- WB stage ----------------
    assign wb_write_data = wb_mem_to_reg ? wb_read_data : wb_alu_result;

endmodule

sim/testbench.v
`timescale 1ns/1ps

module testbench;
    reg clk;
    reg reset;
    integer cycle;

    cpu_top uut (
        .clk(clk),
        .reset(reset)
    );

    // 100 MHz clock (10 ns period)
    initial begin
        clk = 1'b0;
        forever #5 clk = ~clk;
    end

initial begin
    $dumpfile("dump.vcd");
    $dumpvars(0, uut);

    cycle = 0;
    reset = 1'b1;

        // Hold reset for a short duration
        #20;
        reset = 1'b0;

        // Run simulation for multiple cycles
        repeat (35) begin
            @(posedge clk);
            cycle = cycle + 1;
            $display(
                "Cycle=%0d PC=%h | x1=%0d x2=%0d x3=%0d x4=%0d x5=%0d x6=%0d x7=%0d x8=%0d | MEM[0]=%0d",
                cycle,
                uut.pc_current,
                uut.u_regfile.regs[1],
                uut.u_regfile.regs[2],
                uut.u_regfile.regs[3],
                uut.u_regfile.regs[4],
                uut.u_regfile.regs[5],
                uut.u_regfile.regs[6],
                uut.u_regfile.regs[7],
                uut.u_regfile.regs[8],
                uut.u_dmem.mem[0]
            );
        end

        $display("Simulation finished.");
        $finish;
    end
endmodule

dump.vcd
$date
	Wed Mar 11 09:37:03 2026
$end
$version
	Icarus Verilog
$end
$timescale
	1ps
$end
$scope module testbench $end
$scope module uut $end
$var wire 1 ! clk $end
$var wire 1 " reset $end
$var wire 32 # wb_write_data [31:0] $end
$var wire 1 $ wb_reg_write $end
$var wire 32 % wb_read_data [31:0] $end
$var wire 5 & wb_rd [4:0] $end
$var wire 1 ' wb_mem_to_reg $end
$var wire 32 ( wb_alu_result [31:0] $end
$var wire 32 ) pc_next [31:0] $end
$var wire 32 * pc_current [31:0] $end
$var wire 32 + mem_write_data [31:0] $end
$var wire 1 , mem_reg_write $end
$var wire 32 - mem_read_data [31:0] $end
$var wire 5 . mem_rd [4:0] $end
$var wire 1 / mem_mem_write $end
$var wire 1 0 mem_mem_to_reg $end
$var wire 1 1 mem_mem_read $end
$var wire 32 2 mem_alu_result [31:0] $end
$var wire 32 3 if_instruction [31:0] $end
$var wire 5 4 id_rs2 [4:0] $end
$var wire 5 5 id_rs1 [4:0] $end
$var wire 32 6 id_read_data2 [31:0] $end
$var wire 32 7 id_read_data1 [31:0] $end
$var wire 5 8 id_rd [4:0] $end
$var wire 32 9 id_pc [31:0] $end
$var wire 7 : id_opcode [6:0] $end
$var wire 32 ; id_instruction [31:0] $end
$var wire 32 < id_imm_s [31:0] $end
$var wire 32 = id_imm_i [31:0] $end
$var wire 7 > id_funct7 [6:0] $end
$var wire 3 ? id_funct3 [2:0] $end
$var wire 1 @ ex_zero $end
$var wire 5 A ex_rs2 [4:0] $end
$var wire 5 B ex_rs1 [4:0] $end
$var wire 1 C ex_reg_write $end
$var wire 32 D ex_read_data2 [31:0] $end
$var wire 32 E ex_read_data1 [31:0] $end
$var wire 5 F ex_rd [4:0] $end
$var wire 32 G ex_pc [31:0] $end
$var wire 32 H ex_operand_b [31:0] $end
$var wire 1 I ex_mem_write $end
$var wire 1 J ex_mem_to_reg $end
$var wire 1 K ex_mem_read $end
$var wire 32 L ex_imm [31:0] $end
$var wire 1 M ex_alu_src $end
$var wire 32 N ex_alu_result [31:0] $end
$var wire 2 O ex_alu_ctrl [1:0] $end
$var parameter 2 P ALU_ADD $end
$var parameter 2 Q ALU_AND $end
$var parameter 2 R ALU_OR $end
$var parameter 2 S ALU_SUB $end
$var reg 2 T id_alu_ctrl [1:0] $end
$var reg 1 U id_alu_src $end
$var reg 32 V id_imm [31:0] $end
$var reg 1 W id_mem_read $end
$var reg 1 X id_mem_to_reg $end
$var reg 1 Y id_mem_write $end
$var reg 1 Z id_reg_write $end
$scope module u_alu $end
$var wire 32 [ b [31:0] $end
$var wire 1 @ zero $end
$var wire 2 \ alu_ctrl [1:0] $end
$var wire 32 ] a [31:0] $end
$var parameter 2 ^ ALU_ADD $end
$var parameter 2 _ ALU_AND $end
$var parameter 2 ` ALU_OR $end
$var parameter 2 a ALU_SUB $end
$var reg 32 b result [31:0] $end
$upscope $end
$scope module u_dmem $end
$var wire 1 ! clk $end
$var wire 32 c write_data [31:0] $end
$var wire 32 d read_data [31:0] $end
$var wire 1 / mem_write $end
$var wire 1 1 mem_read $end
$var wire 32 e addr [31:0] $end
$var integer 32 f i [31:0] $end
$upscope $end
$scope module u_ex_mem $end
$var wire 1 ! clk $end
$var wire 32 g ex_alu_result [31:0] $end
$var wire 1 " reset $end
$var wire 32 h ex_write_data [31:0] $end
$var wire 1 C ex_reg_write $end
$var wire 5 i ex_rd [4:0] $end
$var wire 1 I ex_mem_write $end
$var wire 1 J ex_mem_to_reg $end
$var wire 1 K ex_mem_read $end
$var reg 32 j mem_alu_result [31:0] $end
$var reg 1 1 mem_mem_read $end
$var reg 1 0 mem_mem_to_reg $end
$var reg 1 / mem_mem_write $end
$var reg 5 k mem_rd [4:0] $end
$var reg 1 , mem_reg_write $end
$var reg 32 l mem_write_data [31:0] $end
$upscope $end
$scope module u_id_ex $end
$var wire 1 ! clk $end
$var wire 2 m id_alu_ctrl [1:0] $end
$var wire 1 U id_alu_src $end
$var wire 32 n id_imm [31:0] $end
$var wire 1 W id_mem_read $end
$var wire 1 X id_mem_to_reg $end
$var wire 1 Y id_mem_write $end
$var wire 5 o id_rd [4:0] $end
$var wire 1 Z id_reg_write $end
$var wire 5 p id_rs1 [4:0] $end
$var wire 5 q id_rs2 [4:0] $end
$var wire 1 " reset $end
$var wire 32 r id_read_data2 [31:0] $end
$var wire 32 s id_read_data1 [31:0] $end
$var wire 32 t id_pc [31:0] $end
$var reg 2 u ex_alu_ctrl [1:0] $end
$var reg 1 M ex_alu_src $end
$var reg 32 v ex_imm [31:0] $end
$var reg 1 K ex_mem_read $end
$var reg 1 J ex_mem_to_reg $end
$var reg 1 I ex_mem_write $end
$var reg 32 w ex_pc [31:0] $end
$var reg 5 x ex_rd [4:0] $end
$var reg 32 y ex_read_data1 [31:0] $end
$var reg 32 z ex_read_data2 [31:0] $end
$var reg 1 C ex_reg_write $end
$var reg 5 { ex_rs1 [4:0] $end
$var reg 5 | ex_rs2 [4:0] $end
$upscope $end
$scope module u_if_id $end
$var wire 1 ! clk $end
$var wire 1 " reset $end
$var wire 32 } if_pc [31:0] $end
$var wire 32 ~ if_instr [31:0] $end
$var reg 32 !" id_instr [31:0] $end
$var reg 32 "" id_pc [31:0] $end
$upscope $end
$scope module u_imem $end
$var wire 32 #" instruction [31:0] $end
$var wire 32 $" addr [31:0] $end
$scope begin $unm_blk_15 $end
$var integer 32 %" i [31:0] $end
$upscope $end
$upscope $end
$scope module u_mem_wb $end
$var wire 1 ! clk $end
$var wire 32 &" mem_alu_result [31:0] $end
$var wire 1 0 mem_mem_to_reg $end
$var wire 5 '" mem_rd [4:0] $end
$var wire 32 (" mem_read_data [31:0] $end
$var wire 1 , mem_reg_write $end
$var wire 1 " reset $end
$var reg 32 )" wb_alu_result [31:0] $end
$var reg 1 ' wb_mem_to_reg $end
$var reg 5 *" wb_rd [4:0] $end
$var reg 32 +" wb_read_data [31:0] $end
$var reg 1 $ wb_reg_write $end
$upscope $end
$scope module u_pc $end
$var wire 1 ! clk $end
$var wire 32 ," next_pc [31:0] $end
$var wire 1 " reset $end
$var reg 32 -" pc_out [31:0] $end
$upscope $end
$scope module u_regfile $end
$var wire 1 ! clk $end
$var wire 5 ." rd [4:0] $end
$var wire 1 $ reg_write $end
$var wire 1 " reset $end
$var wire 5 /" rs1 [4:0] $end
$var wire 5 0" rs2 [4:0] $end
$var wire 32 1" write_data [31:0] $end
$var wire 32 2" read_data2 [31:0] $end
$var wire 32 3" read_data1 [31:0] $end
$var integer 32 4" i [31:0] $end
$upscope $end
$upscope $end
$upscope $end
$scope module testbench $end
$var wire 32 5" x1 [31:0] $end
$upscope $end
$scope module testbench $end
$var wire 32 6" x2 [31:0] $end
$upscope $end
$scope module testbench $end
$var wire 32 7" x3 [31:0] $end
$upscope $end
$scope module testbench $end
$var wire 32 8" x4 [31:0] $end
$upscope $end
$scope module testbench $end
$var wire 32 9" x5 [31:0] $end
$upscope $end
$scope module testbench $end
$var wire 32 :" x6 [31:0] $end
$upscope $end
$scope module testbench $end
$var wire 32 ;" x7 [31:0] $end
$upscope $end
$scope module testbench $end
$var wire 32 <" x8 [31:0] $end
$upscope $end
$enddefinitions $end
$comment Show the parameter values. $end
$dumpall
b1 a
b11 `
b10 _
b0 ^
b1 S
b11 R
b10 Q
b0 P
$end
#0
$dumpvars
b0 <"
b0 ;"
b0 :"
b0 9"
b0 8"
b0 7"
b0 6"
b0 5"
b100000 4"
b0 3"
b0 2"
b0 1"
b0 0"
b0 /"
b0 ."
b0 -"
b100 ,"
b0 +"
b0 *"
b0 )"
b0 ("
b0 '"
b0 &"
b100000000 %"
b0 $"
b10100000000000010010011 #"
b0 ""
b10011 !"
b10100000000000010010011 ~
b0 }
b0 |
b0 {
b0 z
b0 y
b0 x
b0 w
b0 v
b0 u
b0 t
b0 s
b0 r
b0 q
b0 p
b0 o
b0 n
b0 m
b0 l
b0 k
b0 j
b0 i
b0 h
b0 g
b100000000 f
b0 e
b0 d
b0 c
b0 b
b0 ]
b0 \
b0 [
1Z
0Y
0X
0W
b0 V
1U
b0 T
b0 O
b0 N
0M
b0 L
0K
0J
0I
b0 H
b0 G
b0 F
b0 E
b0 D
0C
b0 B
b0 A
1@
b0 ?
b0 >
b0 =
b0 <
b10011 ;
b10011 :
b0 9
b0 8
b0 7
b0 6
b0 5
b0 4
b10100000000000010010011 3
b0 2
01
00
0/
b0 .
b0 -
0,
b0 +
b0 *
b100 )
b0 (
0'
b0 &
b0 %
0$
b0 #
1"
0!
$end
#5000
b100000 4"
1!
#10000
0!
#15000
b100000 4"
1!
#20000
0!
0"
#25000
b101 V
b101 n
1Z
1U
b1 <
b101 =
b101 4
b101 q
b101 0"
b1 8
b1 o
b101000000000000100010011 3
b101000000000000100010011 ~
b101000000000000100010011 #"
1C
1M
b10100000000000010010011 ;
b10100000000000010010011 !"
b1000 )
b1000 ,"
b100 *
b100 }
b100 $"
b100 -"
1!
#30000
0!
#35000
b1010 V
b1010 n
1Z
1U
0@
b101 N
b101 b
b101 g
b10011 3
b10011 ~
b10011 #"
b10 <
b1010 =
b1010 4
b1010 q
b1010 0"
b10 8
b10 o
b101 H
b101 [
b1100 )
b1100 ,"
b1000 *
b1000 }
b1000 $"
b1000 -"
b101000000000000100010011 ;
b101000000000000100010011 !"
b100 9
b100 t
b100 ""
b1 F
b1 i
b1 x
b101 A
b101 |
b101 L
b101 v
1,
1!
#40000
0!
#45000
b1010 N
b1010 b
b1010 g
b0 V
b0 n
1Z
1U
b1010 H
b1010 [
b0 <
b0 =
b0 4
b0 q
b0 0"
b0 8
b0 o
1$
b1 .
b1 k
b1 '"
b101 2
b101 e
b101 j
b101 &"
b10 F
b10 i
b10 x
b1010 A
b1010 |
b1010 L
b1010 v
b100 G
b100 w
b10011 ;
b10011 !"
b1000 9
b1000 t
b1000 ""
b10000 )
b10000 ,"
b1100 *
b1100 }
b1100 $"
b1100 -"
1!
#50000
0!
#55000
1@
b0 N
b0 b
b0 g
b0 H
b0 [
b101 #
b101 1"
b10100 )
b10100 ,"
b10000 *
b10000 }
b10000 $"
b10000 -"
b1100 9
b1100 t
b1100 ""
b0 F
b0 i
b0 x
b0 A
b0 |
b0 L
b0 v
b1000 G
b1000 w
b10 .
b10 k
b10 '"
b1010 2
b1010 e
b1010 j
b1010 &"
b1 &
b1 *"
b1 ."
b101 (
b101 )"
1!
#60000
0!
#65000
b1010 #
b1010 1"
b1000001000000110110011 3
b1000001000000110110011 ~
b1000001000000110110011 #"
b10 &
b10 *"
b10 ."
b1010 (
b1010 )"
b0 .
b0 k
b0 '"
b0 2
b0 e
b0 j
b0 &"
b1100 G
b1100 w
b101 5"
b10000 9
b10000 t
b10000 ""
b11000 )
b11000 ,"
b10100 *
b10100 }
b10100 $"
b10100 -"
1!
#70000
0!
